setup.cfg
setup.py
pyvainglory/__init__.py
pyvainglory/asyncclient.py
pyvainglory/client.py
pyvainglory/clientbase.py
pyvainglory/const.py
pyvainglory/errors.py
pyvainglory/models.py
pyvainglory.egg-info/PKG-INFO
pyvainglory.egg-info/SOURCES.txt
pyvainglory.egg-info/dependency_links.txt
pyvainglory.egg-info/requires.txt
pyvainglory.egg-info/top_level.txt
pyvainglory/data/items.json
pyvainglory/data/skins.json