Metadata-Version: 1.2
Name: pyvainglory
Version: 0.0.2
Summary: A wrapper for the madglory Vainglory API, complete with synchronous and asynchronous client implementations.
Home-page: https://github.com/xKynn/PyVainglory
Author: xKynn
Author-email: xkynn@github.com
License: UNKNOWN
Download-URL: https://github.com/xKynn/PyVainglory/archive/0.0.2.tar.gz
Keywords: vainglory,asyncvainglory,async-vainglory,async_vainglory,pyvainglory
Platform: UNKNOWN
Requires-Python: >=3.5
